{
	"language": "portuguese",
	"none": "Nada",
	"MetersPerSecond_Abbreviation": "m/s",
	"Button_OK": "OK",
	"Button_Cancel": "Cancelar",
	"Button_Close": "Fechar",
	"Button_Delete": "Eliminar",
	"Button_Replace": "Substituir",
	"Button_Discard": "Ignorar",
	"Button_Save": "Guardar",
	"Button_Done": "OK",
	"Button_Back": "Voltar",
	"Button_Next": "Seguinte",
	"Button_Retry": "Tentar de novo",
	"Settings": "Definições",
	"PowerMenuResetSeatedPosition": "Repor posição sentada",
	"PowerMenuResetStandingPosition": "Repor posição de pé",
	"Resetting_Countdown": "A repor...",
	"PowerMenuTurnOffController": "Desligar comando",
	"PowerMenuQuitSceneApp": "Sair de %1$s",
	"PowerMenuQuitSceneApp_NoApp": "Sair da aplicação",
	"PowerMenuExitVR": "Sair da R.V.",
	"PowerMenuCancel": "Cancelar",
	"PowerMenuSteamOverlay": "Steam",
	"PowerMenuHeader": "Menu de energia",
	"IPD_Description": "Distância entre as lentes",
	"NoSteamWarning": "Steam indisponível. Algumas funcionalidades podem estar desativadas.",
	"WakingUpBaseStations": "A despertar estações-base...",
	"/input/joystick": "Joystick",
	"/input/trackpad": "Trackpad",
	"/input/trigger": "Gatilho",
	"/input/grip": "Empunhadura",
	"/input/application_menu": "Menu",
	"/input/system": "System",
	"/proximity": "Sensor de proximidade",
	"/input/a": "Botão A",
	"/input/b": "Botão B",
	"/input/x": "Botão X",
	"/input/y": "Botão Y",
	"/pose/raw": "Dados brutos",
	"/pose/base": "Base",
	"/pose/tip": "Extremidade",
	"/pose/gdc2015": "GDC",
	"/pose/handgrip": "(Empunhadura)",
	"/input/skeleton/left": "Esqueleto esquerdo",
	"/input/skeleton/right": "Esqueleto direito",
	"/output/haptic": "Háptica",
	"/user/hand/right": "Mão direita",
	"/user/hand/left": "Mão esquerda",
	"/user/hand/primary": "Mão dominante",
	"/user/hand/secondary": "Mão secundária",
	"/user/hand/any": "Qualquer mão",
	"/user/stylus": "Stylus",
	"/user/gamepad": "Comando",
	"/user/foot/left": "Pé esquerdo",
	"/user/foot/right": "Pé direito",
	"/user/shoulder/left": "Ombro esquerdo",
	"/user/shoulder/right": "Ombro direito",
	"/user/waist": "Cintura",
	"/user/chest": "Peito",
	"/user/camera": "Câmara",
	"/user/keyboard": "Teclado",
	"InputSourceName": "%2$s/%1$s/%3$s",
	"OriginString_All": "%2$s/%1$s/%3$s",
	"OriginString_HandController": "%2$s/%1$s",
	"OriginString_HandSource": "%1$s/%3$s",
	"OriginString_Hand": "%1$s",
	"OriginString_ControllerSource": "%2$s/%3$s",
	"OriginString_Source": "%3$s",
	"OriginString_Controller": "%2$s",
	"KeyboardDone": "OK",
	"DO_NOT_TRANSLATE": "IgnoreMe"
}
